cmdx.py
cmdx-0.6.4.dist-info/METADATA
cmdx-0.6.4.dist-info/WHEEL
cmdx-0.6.4.dist-info/top_level.txt
cmdx-0.6.4.dist-info/RECORD
