Metadata-Version: 2.1
Name: cmdx
Version: 0.6.4
Summary: A fast subset of maya.cmds
Home-page: https://github.com/mottosso/cmdx
Author: Marcus Ottosson
Author-email: me@mottosso.com
License: BSD
Keywords: Fast subset of maya.cmds
Classifier: Development Status :: 5 - Production/Stable
Classifier: License :: OSI Approved :: BSD License
Classifier: Intended Audience :: Developers
Classifier: Operating System :: OS Independent
Classifier: Programming Language :: Python
Classifier: Programming Language :: Python :: 2
Classifier: Programming Language :: Python :: 2.7
Classifier: Programming Language :: Python :: 3
Classifier: Programming Language :: Python :: 3.6
Classifier: Programming Language :: Python :: 3.7
Classifier: Topic :: Utilities
Classifier: Topic :: Software Development
Classifier: Topic :: Software Development :: Libraries :: Python Modules
